papyr/__init__.py
papyr-0.0.1.dist-info/METADATA
papyr-0.0.1.dist-info/WHEEL
papyr-0.0.1.dist-info/top_level.txt
papyr-0.0.1.dist-info/RECORD
