Metadata-Version: 2.1
Name: papyr
Version: 0.0.1
Summary: Papyr
Home-page: https://github.com/dgarana/papyr
Author: David Garaña
License: UNKNOWN
Keywords: console development
Platform: UNKNOWN
Classifier: Development Status :: 3 - Alpha
Classifier: Intended Audience :: Developers
Classifier: Topic :: Software Development :: Build Tools
Classifier: License :: OSI Approved :: MIT License
Classifier: Programming Language :: Python :: 3.4
Classifier: Programming Language :: Python :: 3.5
Classifier: Programming Language :: Python :: 3.6
Classifier: Programming Language :: Python :: 3.7
